nonebot_plugin_dog/__init__.py
nonebot_plugin_dog/check.py
nonebot_plugin_dog/handle.py
nonebot_plugin_dog/update.py
nonebot_plugin_dog/utils.py
nonebot_plugin_dog-0.3.1.dist-info/LICENSE
nonebot_plugin_dog-0.3.1.dist-info/METADATA
nonebot_plugin_dog-0.3.1.dist-info/WHEEL
nonebot_plugin_dog-0.3.1.dist-info/top_level.txt
nonebot_plugin_dog-0.3.1.dist-info/RECORD
