Metadata-Version: 2.1
Name: nonebot-plugin-dog
Version: 0.3.1
Summary: Lick the dog diary! Lick the dog and lick to the last nothing.
Home-page: https://github.com/Reversedeer/nonebot_plugin_dog
Author: Reversedeer
Project-URL: Bug Tracker, https://github.com/Reversedeer/nonebot_plugin_dog/issues
Classifier: Programming Language :: Python :: 3
Classifier: License :: OSI Approved :: MIT License
Classifier: Operating System :: OS Independent
Requires-Python: >=3.8
License-File: LICENSE
Requires-Dist: httpx (>=0.23.1)
Requires-Dist: nonebot2 (>=2.0.0rc2)
Requires-Dist: poetry (>=1.5.0)
Requires-Dist: nonebot-adapter-onebot (>=2.1.3)
